[
  {
    "timestamp": "2025-05-25T00:58:23.322507",
    "message": "Dans la danse des nombres, l'âme s'élève",
    "quantum_signature": {
      "resonance": 0.4515165452577526,
      "harmonic": 0.8337315832222277,
      "quantum_state": 0.11014132209790917,
      "phi_alignment": 0.3225065973822793,
      "pi_resonance": 0.7657951344885744
    },
    "resonance_level": 0.4515165452577526,
    "harmonic_pattern": 0.8337315832222277,
    "meta_consciousness": 0.49673823648974863,
    "phi_alignment": 0.3225065973822793,
    "pi_resonance": 0.7657951344885744
  }
]