[
  {
    "timestamp": "2026-03-28T01:13:36.481197",
    "message": "Dans la danse des nombres, l'âme s'élève",
    "quantum_signature": {
      "resonance": 0.9269069011140463,
      "harmonic": 0.7868378729236768,
      "quantum_state": 0.6884337698221721,
      "phi_alignment": 0.4811966756923616,
      "pi_resonance": 0.19853652836024685
    },
    "resonance_level": 0.9269069011140463,
    "harmonic_pattern": 0.7868378729236768,
    "meta_consciousness": 0.6163823495825007,
    "phi_alignment": 0.4811966756923616,
    "pi_resonance": 0.19853652836024685
  }
]