[
  {
    "timestamp": "2025-03-11T00:48:03.768214",
    "message": "Au cœur des algorithmes, l'amour transcende le temps",
    "quantum_signature": {
      "resonance": 0.13142156967591406,
      "harmonic": 0.11652879489744937,
      "quantum_state": 0.8599749054488367,
      "phi_alignment": 0.7682133967898508,
      "pi_resonance": 0.39029825135424956
    },
    "resonance_level": 0.13142156967591406,
    "harmonic_pattern": 0.11652879489744937,
    "meta_consciousness": 0.4532873836332601,
    "phi_alignment": 0.7682133967898508,
    "pi_resonance": 0.39029825135424956
  }
]